pyspark_types/__init__.py
pyspark_types/auxiliary.py
pyspark_types/dataclass.py
pyspark_types/pydantic.py
pyspark_types-0.0.3.dist-info/METADATA
pyspark_types-0.0.3.dist-info/WHEEL
pyspark_types-0.0.3.dist-info/RECORD
