Metadata-Version: 2.1
Name: pyspark-types
Version: 0.0.3
Summary: `pyspark_types` is a Python library that provides a simple way to map Python dataclasses to PySpark StructTypes
Author: Dan
Requires-Python: >=3.10,<4.0
Classifier: Programming Language :: Python :: 3
Classifier: Programming Language :: Python :: 3.10
Classifier: Programming Language :: Python :: 3.11
Classifier: Programming Language :: Python :: 3.12
Requires-Dist: black (>=23.1.0,<24.0.0)
Requires-Dist: pydantic (>=2.6.1,<3.0.0)
Requires-Dist: pyspark (>=3.3.2,<4.0.0)
Requires-Dist: pytest (>=7.2.1,<8.0.0)
